stream_video/__init__.py
stream_video/client.py
stream_video/gen/__init__.py
stream_video/gen/validate/validate_pb2.py
stream_video/gen/validate/validate_pb2.pyi
stream_video/gen/validate/validate_twirp.py
stream_video/gen/video/__init__.py
stream_video/gen/video/coordinator/__init__.py
stream_video/gen/video/coordinator/app_v1/app_pb2.py
stream_video/gen/video/coordinator/app_v1/app_pb2.pyi
stream_video/gen/video/coordinator/app_v1/app_twirp.py
stream_video/gen/video/coordinator/broadcast_v1/broadcast_pb2.py
stream_video/gen/video/coordinator/broadcast_v1/broadcast_pb2.pyi
stream_video/gen/video/coordinator/broadcast_v1/broadcast_twirp.py
stream_video/gen/video/coordinator/call_v1/call_pb2.py
stream_video/gen/video/coordinator/call_v1/call_pb2.pyi
stream_video/gen/video/coordinator/call_v1/call_twirp.py
stream_video/gen/video/coordinator/client_v1_rpc/client_rpc_pb2.py
stream_video/gen/video/coordinator/client_v1_rpc/client_rpc_pb2.pyi
stream_video/gen/video/coordinator/client_v1_rpc/client_rpc_twirp.py
stream_video/gen/video/coordinator/client_v1_rpc/envelopes_pb2.py
stream_video/gen/video/coordinator/client_v1_rpc/envelopes_pb2.pyi
stream_video/gen/video/coordinator/client_v1_rpc/envelopes_twirp.py
stream_video/gen/video/coordinator/client_v1_rpc/websocket_pb2.py
stream_video/gen/video/coordinator/client_v1_rpc/websocket_pb2.pyi
stream_video/gen/video/coordinator/client_v1_rpc/websocket_twirp.py
stream_video/gen/video/coordinator/edge_v1/edge_pb2.py
stream_video/gen/video/coordinator/edge_v1/edge_pb2.pyi
stream_video/gen/video/coordinator/edge_v1/edge_twirp.py
stream_video/gen/video/coordinator/event_v1/event_pb2.py
stream_video/gen/video/coordinator/event_v1/event_pb2.pyi
stream_video/gen/video/coordinator/event_v1/event_twirp.py
stream_video/gen/video/coordinator/geofence_v1/geofence_pb2.py
stream_video/gen/video/coordinator/geofence_v1/geofence_pb2.pyi
stream_video/gen/video/coordinator/geofence_v1/geofence_twirp.py
stream_video-0.0.6.dist-info/LICENSE
stream_video-0.0.6.dist-info/WHEEL
stream_video-0.0.6.dist-info/METADATA
stream_video-0.0.6.dist-info/RECORD
